{
    "type": "mekanism:reaction",
    "duration": 600,
    "energyRequired": 200,
    "fluidInput": {
      "amount": 100,
      "fluid": "kubejs:calcium_hydroxide"
    },
    "gasInput": {
      "amount": 1,
      "gas": "mekanismelements:ammonia"
    },
    "itemInput": {
      "amount": 2,
      "ingredient": {
        "item": "chemlib:sodium_chloride"
      }
    },
    "itemOutput": {
      "count": 1,
      "item": "chemlib:sodium_carbonate"
    },
    "gasOutput": {
      "amount": 100,
      "gas": "kubejs:calcium_chloride"
    }
}