{
    "entity": "ad_astra:martian_raptor",
    "variants": [],
    "name": "entity.ad_astra.martian_raptor",
    "name_color": "#3E632B",
    "gui_scale": 1,
    "gui_x_offset": 0,
    "gui_y_offset": 0,
    "gui_z_offset": 0,
    "sim_cost": 10240,
    "input": {
        "item": "hostilenetworks:prediction_matrix"
    },
    "base_drop": {
        "item": "kubejs:sky_prediction"
    },
    "trivia": "kubejs.trivia.martian_raptor",
    "fabricator_drops": [
        {
            "item": "ad_astra:ostrum_nugget",
            "count": 32
        },
        {
            "item": "biomancy:mob_fang",
            "count": 8
        }
    ],
    "tier_data": [
        6,
        54,
        354,
        1254
    ],
    "data_per_kill": [
        1,
        4,
        10,
        18
    ]
}